{
  "description": "A country record.",
  "properties": {
    "id": {
      "title": "ID",
      "description": "ISO 3166-1 alpha-3 code."
    },
    "name": {
      "title": "Name",
      "description": "Country name."
    },
    "isoCode": {
      "title": "ISO Code",
      "description": "ISO 3166-1 alpha-2 code (aka cTLD)."
    },
    "capitalCity": {
      "title": "Capital",
      "description": "Capital city."
    },
    "longitude": {
      "title": "Longitude",
      "description": "W/E geographic coordinate."
    },
    "latitude": {
      "title": "Latitude",
      "description": "N/S geographic coordinate."
    }
  },
  "required": [
    "id",
    "name",
    "isoCode"
  ]
}
